meteoswissdata/__init__.py
meteoswissdata/station_measurements.py
meteoswissdata/station_measurements_test.py
meteoswissdata-0.1.1.dist-info/LICENSE
meteoswissdata-0.1.1.dist-info/METADATA
meteoswissdata-0.1.1.dist-info/WHEEL
meteoswissdata-0.1.1.dist-info/top_level.txt
meteoswissdata-0.1.1.dist-info/RECORD
