Metadata-Version: 2.1
Name: meteoswissdata
Version: 0.1.1
Summary: Python library to pull weather data from MeteoSwiss.
Home-page: https://github.com/allestuetsmerweh/meteoswissdata
Author: Simon Hatt
Author-email: allestuetsmerweh@gmail.com
License: UNKNOWN
Platform: UNKNOWN
Classifier: Programming Language :: Python :: 3
Classifier: License :: OSI Approved :: MIT License
Classifier: Operating System :: OS Independent
Requires-Python: >=3.6
